{
 "absolute_value": 0,
 "align_labels_right": 0,
 "creation": "2023-12-20 13:23:56.711307",
 "css": ".print-format .table-bordered td, .print-format .table-bordered th {\r\n    border: 1px solid #f4f5f6 !important;\r\n    border-color: #000 !important;\r\n}\r\n\r\n.print-format .letter-head {\r\n    margin-bottom: 2px ;\r\n}\r\n\r\n.table {\r\n    font-size: inherit;\r\n    margin:0px !important   ;\r\n}",
 "custom_format": 1,
 "default_print_language": "en",
 "disabled": 0,
 "doc_type": "Excel Credit Limit Enhancement Form",
 "docstatus": 0,
 "doctype": "Print Format",
 "font_size": 14,
 "html": "<div id=\"header-html\" class=\"hidden-pdf row section-break\">\n\t\t\n\t<div class=\"letter-head\"><div><img src=\"https://bd.bazrabd.org/files/ETL-header.jpg\" style=\"width: 862px;\"><br></div></div>\t\t    \n\t\t<div class=\"print-heading\" style=\"padding-bottom: 6px !important; margin-bottom: 3px;\">\n\t\t\t\n\t\t\t<div class=\"2nd-head\" style=\"padding-top: 6px !important;\">\n\t\t\t\t<p style=\"display: inline-block; text-align: left; width: 33%; \">{{ doc.name }}</p>\n\t\t\t\t<p style=\"display: inline-block; text-align: center; width: 32%; \"><b>Excel Credit Limit Enhancement Form</b></p>\n\t\t\t\t<p style=\"display: inline-block; text-align: right; width: 33%;\">{{ doc.get_formatted(\"territory\") }}</p>\n\t\t\t</div> \n\t\t\t\n\t\t\t\t\t\n\t<div>\n\t\t{%- if doc.docstatus == 0 -%}\n\t\t\t<p class=\"text-center\"><b>Draft</b></p>\n\t\t{% else %}\n\t\t{%- endif %}\n\t</div>\n\n\t\t</div>\n\t\n\t</div>\n\n\n\t\t<div class=\"row section-break\" style=\"margin: 2px !important\">\n\t\t\t<table class=\"col-xs-6\">\n\t\t\t\t<tr>\n\t\t\t\t\t<td style=\"padding: 2px !important;\">Customer Name</td>\n\t\t\t\t\t<td style=\"padding: 2px 16px !important;\" class=\"text-center\">:</td>\n\t\t\t\t\t<td style=\"padding: 2px !important;\">{{ doc.get_formatted(\"customer_name\") }}</td>\n\t\t\t\t</tr>\n\t\t\t\t<tr>\n\t\t\t\t\t<td style=\"padding: 2px !important;\">Customer Group</td>\n\t\t\t\t\t<td style=\"padding: 2px 16px !important;\" class=\"text-center\">:</td>\n\t\t\t\t\t<td style=\"padding: 2px !important;\">{{ doc.get_formatted(\"customer_group\") }}</td>\n\t\t\t\t</tr>\n\t\t\t\t<tr>\n\t\t\t\t\t<td style=\"padding: 2px !important;\">Actual Cust. Code</td>\n\t\t\t\t\t<td style=\"padding: 2px 16px !important;\" class=\"text-center\">:</td>\n\t\t\t\t\t<td style=\"padding: 2px !important;\">{{ doc.get_formatted(\"excel_actual_cust_code\") }}</td>\n\t\t\t\t</tr>\n\t\t\t\t<tr>\n\t\t\t\t\t<td style=\"padding: 2px !important;\">Sales Person</td>\n\t\t\t\t\t<td style=\"padding: 2px !important;\" class=\"text-center\">:</td>\n\t\t\t\t\t<td style=\"padding: 2px !important;\">{{  doc.get_formatted(\"excel_sales_person\") }}</td>\n\t\t\t\t</tr>\n                \n                <tr>\n\t\t\t\t\t<td style=\"padding: 2px !important;\">Supervisor Name</td>\n\t\t\t\t\t<td style=\"padding: 2px !important;\" class=\"text-center\">:</td>\n\t\t\t\t\t<td style=\"padding: 2px !important;\">{{  doc.get_formatted(\"supervisor_name\") }}</td>\n\t\t\t\t</tr>\n\n\t\t\t\t\n\t\t\t</table>\n\n\t\t\t<table class=\"col-xs-1\">\n\t\t\t\t<tr><td></td></tr>\n\t\t\t</table>\n\n\t\t\t<table class=\"col-xs-5\">\n\t\t\t\t<tr>\n\t\t\t\t\t<td style=\"padding: 2px !important;\" >Posting Date</td>\n\t\t\t\t\t<td style=\"padding: 2px !important;\" class=\"text-center\">:</td>\n\t\t\t\t\t<td style=\"padding: 2px !important;\" class=\"text-right\">{{ doc.get_formatted(\"posting_date\") }}</td>\n\t\t\t\t</tr>\n\t\t\t\t<tr>\n\t\t\t\t\t<td style=\"padding: 2px !important;\">Customer Address</td>\n\t\t\t\t\t<td style=\"padding: 2px !important;\" class=\"text-center\">:</td>\n\t\t\t\t\t<td style=\"padding: 2px !important;\" class=\"text-right\">{{ doc.get_formatted(\"address\") }}</td>\n\t\t\t\t</tr>\n\t\t\t\t\n\t\t\t\t<tr>\n\t\t\t\t\t<td style=\"padding: 2px !important; padding-right: 2px !important;\"><b>Approved Status</b></td>\n\t\t\t\t\t<td style=\"padding: 2px !important;\" class=\"text-center\">:</td>\n\t\t\t\t\t<td style=\"padding: 2px !important;\" class=\"text-right\"><b>{{  doc.get_formatted(\"workflow_state\") }}</b></td>\n\t\t\t\t</tr>\n\t\t\t\t\n\t\t\t</table>\n\n\t\t</div>\n\n\n\n        <table>\n            <tr>\n                <td> <b>Sales Person Remarks :</b> {{ doc.get_formatted(\"remarks\") }}</td>\n            </tr>\n        </table>\n\n\n    <p class=\"text-center\" style=\"font-style: initial; font-size: 20px; text-align: center;\"> <u>Excel CLE Details</u> </p>\n\n    <table style=\"  border: 2px solid black; border-collapse: collapse;\" class=\"table table-bordered border-5 border-dark\"  >\n        <tr>\n            <td style=\"padding-left: 2px !important; padding-right: 0px !important; padding-right: 2px !important;  width: 25%;\"> <b>Type of New Credit Limit</b> </td>\n \n            <td style=\"padding-left: 2px !important; width: 25%\"  class=\"text-left\"> <b> {{  doc.get_formatted(\"type_of_new_credit_limit\") }} </b></td>\n\n\t\t\t<td style=\"padding-left: 2px !important; padding-right: 0px !important; padding-right: 2px !important; width: 1%;\"> </td>\n            \n            <td style=\"padding-left: 2px !important; padding-right: 0px !important; padding-right: 2px !important;  width: 24%;\"> <b>Start Business with Excel (year)</b> </td>\n \n            <td style=\"padding-left: 2px !important; width: 25%;\"  class=\"text-left\"> {{  doc.get_formatted(\"start_business_with_excel_year\") }} </td>\n        </tr>\n        <tr>\n            <td style=\"padding-left: 2px !important; padding-right: 0px !important; padding-right: 2px !important;  width: 1800px;\"> <b>Proposed Credit Limit Amount</b> </td>\n \n            <td style=\"padding-left: 2px !important; width: 400px\"  class=\"text-left\"> <b> {{ doc.proposed_credit_limit_amount }} </b></td>\n\n\t\t\t<td style=\"padding-left: 2px !important; padding-right: 0px !important; padding-right: 2px !important; width: 0px;\"> </td>\n            \n            <td style=\"padding-left: 2px !important; padding-right: 0px !important; padding-right: 2px !important;  width: 1800px;\"> <b>Interested Brand</b> </td>\n \n            <td style=\"padding-left: 2px !important; width: 400px;\"  class=\"text-left\"> {{  doc.get_formatted(\"interested_brand\") }} </td>\n        </tr>\n        <tr>\n            <td style=\"padding-left: 2px !important; padding-right: 0px !important; padding-right: 2px !important;  width: 1800px;\"> <b>Adjustment Date</b> </td>\n \n            <td style=\"padding-left: 2px !important; width: 400px\"  class=\"text-left\"> {{  doc.get_formatted(\"adjustment_date\") }} </td>\n\n\t\t\t<td style=\"padding-left: 2px !important; padding-right: 0px !important; padding-right: 2px !important; width: 0px;\"> </td>\n            \n            <td style=\"padding-left: 2px !important; padding-right: 0px !important; padding-right: 2px !important;  width: 1800px;\"> <b>Last Year Turn Over</b> </td>\n \n            <td style=\"padding-left: 2px !important; width: 400px;\"  class=\"text-left\"> {{  doc.last_year_turn_over }} </td>\n        </tr>\n        <tr>\n            <td style=\"padding-left: 2px !important; padding-right: 0px !important; padding-right: 2px !important;  width: 1800px;\"> <b>Fixed Limit</b> </td>\n \n            <td style=\"padding-left: 2px !important; width: 400px\"  class=\"text-left\"> {{  doc.fixed_limit }} </td>\n\n\t\t\t<td style=\"padding-left: 2px !important; padding-right: 0px !important; padding-right: 2px !important; width: 0px;\"> </td>\n            \n            <td style=\"padding-left: 2px !important; padding-right: 0px !important; padding-right: 2px !important;  width: 1800px;\"> <b>Average Monthly Sales (Last Year)</b> </td>\n \n            <td style=\"padding-left: 2px !important; width: 400px;\"  class=\"text-left\"> {{  doc.average_monthly_sales|round(2) }} </td>\n        </tr>\n        <tr>\n            <td style=\"padding-left: 2px !important; padding-right: 0px !important; padding-right: 2px !important;  width: 1800px;\"> <b>Current Credit Limit</b> </td>\n \n            <td style=\"padding-left: 2px !important; width: 400px\"  class=\"text-left\"> <b> {{  doc.current_credit_limit }} </b></td>\n\n\t\t\t<td style=\"padding-left: 2px !important; padding-right: 0px !important; padding-right: 2px !important; width: 0px;\"> </td>\n            \n            <td style=\"padding-left: 2px !important; padding-right: 0px !important; padding-right: 2px !important;  width: 1800px;\"> <b>Last Year Collection</b> </td>\n \n            <td style=\"padding-left: 2px !important; width: 400px;\"  class=\"text-left\"> {{  doc.excel_last_year_collection }} </td>\n        </tr>\n\n        <tr>\n            <td style=\"padding-left: 2px !important; padding-right: 0px !important; padding-right: 2px !important;  width: 1800px;\"> <b>Current Year Sales</b> </td>\n \n            <td style=\"padding-left: 2px !important; width: 400px\"  class=\"text-left\"> <b> {{  doc.current_year_sales }} </b></td>\n\n\t\t\t<td style=\"padding-left: 2px !important; padding-right: 0px !important; padding-right: 2px !important; width: 0px;\"> </td>\n            \n            <td style=\"padding-left: 2px !important; padding-right: 0px !important; padding-right: 2px !important;  width: 1800px;\"> <b>Average Monthly Collection (Last Year)</b> </td>\n \n            <td style=\"padding-left: 2px !important; width: 400px;\"  class=\"text-left\"> {{  doc.excel_average_monthly_collection_last_year|round(2) }} </td>\n        </tr>\n\n        <tr>\n            <td style=\"padding-left: 2px !important; padding-right: 0px !important; padding-right: 2px !important;  width: 1800px;\"> <b>Average Monthly Sales (Current Year)</b> </td>\n \n            <td style=\"padding-left: 2px !important; width: 400px\"  class=\"text-left\"> {{ doc.average_monthly_sales_current_year|round(2) }} </td>\n\n\t\t\t<td style=\"padding-left: 2px !important; padding-right: 0px !important; padding-right: 2px !important; width: 0px;\"> </td>\n            \n            <td style=\"padding-left: 2px !important; padding-right: 0px !important; padding-right: 2px !important;  width: 1800px;\"> <b>Current Outstanding</b> </td>\n \n            <td style=\"padding-left: 2px !important; width: 400px;\"  class=\"text-left\"> {{  doc.current_outstanding }} </td>\n        </tr>\n\n        <tr>\n            <td style=\"padding-left: 2px !important; padding-right: 0px !important; padding-right: 2px !important;  width: 1800px;\"> <b>Current Year Collection</b> </td>\n \n            <td style=\"padding-left: 2px !important; width: 400px\"  class=\"text-left\"> {{  doc.excel_current_year_collection }} </td>\n\n\t\t\t<td style=\"padding-left: 2px !important; padding-right: 0px !important; padding-right: 2px !important; width: 0px;\"> </td>\n            \n            <td style=\"padding-left: 2px !important; padding-right: 0px !important; padding-right: 2px !important;  width: 1800px;\"> <b>Last Month Sales</b> </td>\n \n            <td style=\"padding-left: 2px !important; width: 400px;\"  class=\"text-left\"> {{  doc.last_month_sales }} </td>\n        </tr>\n\n\t\t<tr>\n            <td style=\"padding-left: 2px !important; padding-right: 0px !important; padding-right: 2px !important;  width: 1800px;\"> <b>Average Monthly Collection (Current Year)</b> </td>\n \n            <td style=\"padding-left: 2px !important; width: 400px\"  class=\"text-left\"> {{  doc.excel_average_monthly_collection_current_year|round(2) }} </td>\n\n\t\t\t<td style=\"padding-left: 2px !important; padding-right: 0px !important; padding-right: 2px !important; width: 0px;\"> </td>\n            \n            <td style=\"padding-left: 2px !important; padding-right: 0px !important; padding-right: 2px !important;  width: 1800px;\"> <b>Cheque In Hand Amount</b> </td>\n \n            <td style=\"padding-left: 2px !important; width: 400px\"  class=\"text-left\"> <b> {{  doc.cheque_in_hand_amount }} </b></td>\n        </tr>\n\n\t\t<tr>\n            <td style=\"padding-left: 2px !important; padding-right: 0px !important; padding-right: 2px !important;  width: 1800px;\"> <b>Bank Name</b> (Security Cheque) </td>\n \n            <td style=\"padding-left: 2px !important; width: 400px\"  class=\"text-left\"> {{  doc.get_formatted(\"bank_name\") }} </td>\n\n\t\t\t<td style=\"padding-left: 2px !important; padding-right: 0px !important; padding-right: 2px !important; width: 0px;\"> </td>\n            \n            <td style=\"padding-left: 2px !important; padding-right: 0px !important; padding-right: 2px !important;  width: 1800px;\"> <b>Cheque No</b> (Security Cheque) </td>\n \n            <td style=\"padding-left: 2px !important; width: 400px\"  class=\"text-left\"> {{  doc.get_formatted(\"cheque_no\") }} </td>\n        </tr>\n\n\t\t<tr>\n            <td style=\"padding-left: 2px !important; padding-right: 0px !important; padding-right: 2px !important;  width: 1800px;\"> <b>Account No</b> (Security Cheque) </td>\n \n            <td style=\"padding-left: 2px !important; width: 400px\"  class=\"text-left\"> {{  doc.get_formatted(\"account_no\") }} </td>\n\n\t\t\t<td style=\"padding-left: 2px !important; padding-right: 0px !important; padding-right: 2px !important; width: 0px;\"> </td>\n            \n            <td style=\"padding-left: 2px !important; padding-right: 0px !important; padding-right: 2px !important;  width: 1800px;\"> <b>Amount</b> (Security Cheque) </td>\n \n            <td style=\"padding-left: 2px !important; width: 400px\"  class=\"text-left\"> {{  doc.amount }} </td>\n        </tr>\n\n\t\t<tr>\n            <td style=\"padding-left: 2px !important; padding-right: 0px !important; padding-right: 2px !important;  width: 1800px;\"> <b>Supervisor Remarks</b> </td>\n\n            <td style=\"padding-left: 2px !important; width: 400px\" class=\"text-left\">{{  doc.get_formatted(\"excel_supervisor_remarks\") }}</td>\n\n\t\t\t<td style=\"padding-left: 2px !important; padding-right: 0px !important; padding-right: 2px !important; width: 0px;\"> </td>\n\n            <td style=\"padding-left: 2px !important; padding-right: 0px !important; padding-right: 2px !important;  width: 1800px;\"> <b>Head of Finance Remarks</b> </td>\n\n            <td style=\"padding-left: 2px !important; width: 400px\" class=\"text-left\">{{  doc.get_formatted(\"excel_hof_remarks\") }}</td>\n        </tr>\n\n\t\t<tr>\n            <td style=\"padding-left: 2px !important; padding-right: 0px !important; padding-right: 2px !important;  width: 1800px;\"> <b>Head Of Sales Remarks</b> </td>\n\n            <td style=\"padding-left: 2px !important; width: 400px\" class=\"text-left\">{{  doc.get_formatted(\"excel_hos_remarks\") }}</td>\n\n\t\t\t<td style=\"padding-left: 2px !important; padding-right: 0px !important; padding-right: 2px !important; width: 0px;\"> </td>\n\n            <td style=\"padding-left: 2px !important; padding-right: 0px !important; padding-right: 2px !important;  width: 1800px;\"> <b>Director Remarks</b> </td>\n\n            <td style=\"padding-left: 2px !important; width: 400px\" class=\"text-left\">{{  doc.get_formatted(\"excel_director_remarks\") }}</td>\n        </tr>\n\n        <tr>\n            <td style=\"padding-left: 2px !important; padding-right: 0px !important; padding-right: 2px !important;  width: 1800px;\"> <b>CM Remarks</b> </td>\n\n            <td style=\"padding-left: 2px !important; width: 400px\" class=\"text-left\">{{  doc.get_formatted(\"excel_cm_remarks\") }}</td>\n\n\t\t\t<td style=\"padding-left: 2px !important; padding-right: 0px !important; padding-right: 2px !important; width: 0px;\"> </td>\n\n            <td style=\"padding-left: 2px !important; padding-right: 0px !important; padding-right: 2px !important;  width: 1800px;\"> <b>Managing Director Remarks</b> </td>\n\n            <td style=\"padding-left: 2px !important; width: 400px\" class=\"text-left\">{{  doc.get_formatted(\"excel_md_remarks\") }}</td>\n        </tr>\n\t</table>\n\n\n\n\n\t<footer>\n\n\t\t<div id=\"footer-html\" class=\"visible-pdf\" style=\"display: block !important; order: 1;\">\n\t\n\t\t\t<div class=\"letter-head-footer\">\n\n\t\t\t\t<!--<p style=\"text-align: left; display: inline-block; width: 49.70%;\"><b style=\"border-top: 2px solid #000;\">Receiver's Signature</b></p>-->\n\t\t\t\t<!--<p style=\"text-align: right; display: inline-block; width: 49.70%;\"><b style=\"border-top: 2px solid #000;\">Accounts Signature</b></p>-->\n\t\t\t\t<div>\n\t\t\t\t\t<img src=\"https://bd.bazrabd.org/files/SINV%20Futter%20all%20use%20final-01.jpg\" style=\"width: 862px;\">\n\t\t\t\t</div>\n\t\t\t</div>\n\t\n\t\t\t<p class=\"text-center small page-number visible-pdf\">\n\t\t\t\tPage <span class=\"page\"></span> of <span class=\"topage\"></span>\n\t\t\t</p>\n\t\t</div>\n\n\t</footer>",
 "idx": 0,
 "line_breaks": 0,
 "margin_bottom": 15.0,
 "margin_left": 15.0,
 "margin_right": 15.0,
 "margin_top": 15.0,
 "modified": "2023-12-24 13:43:00.814903",
 "modified_by": "Administrator",
 "module": "Excel Hr",
 "name": "CLE Print Format",
 "page_number": "Hide",
 "print_format_builder": 0,
 "print_format_builder_beta": 0,
 "print_format_type": "Jinja",
 "raw_printing": 0,
 "show_section_headings": 0,
 "standard": "Yes"
}